LICENSE
MANIFEST.in
README.rst
setup.py
docs/Makefile
docs/changes.rst
docs/conf.py
docs/dom.rst
docs/event.rst
docs/index.rst
docs/node.rst
docs/reference.rst
docs/tag.rst
docs/_static/custom.css
docs/_static/custom_ja.css
docs/_static/honoka.min.css
docs/_static/skyblue.min.css
docs/_static/umi.min.css
docs/_static/css/bagpakk.min.css
docs/_static/css/baseguide.min.css
docs/_static/css/bijou.min.css
docs/_static/css/groundwork.css
docs/_static/css/kathamo.min.css
docs/_static/css/kube.min.css
docs/_static/css/pure-extra.css
docs/_static/css/schema.min.css
docs/_static/css/siimple.min.css
docs/_static/css/skyblue.min.css
docs/_static/css/spark.min.css
docs/_static/css/spectre.min.css
docs/_templates/layout.html
docs/guide/index.rst
tests/__init__.py
tests/base.py
tests/test_css.py
tests/test_document.py
tests/test_element.py
tests/test_event.py
tests/test_imports.py
tests/test_node.py
tests/test_options.py
tests/test_parser.py
tests/test_tag.py
tests/test_testing.py
tests/test_themes.py
tests/test_web_node.py
tests/test_window.py
tests/server/__init__.py
tests/server/base.py
tests/server/test_server.py
tests/test_pyppeteer/__init__.py
tests/test_pyppeteer/base.py
tests/test_pyppeteer/test_examples.py
tests/test_pyppeteer/test_node.py
tests/test_pyppeteer/test_tag.py
tests/test_selenium/__init__.py
tests/test_selenium/base.py
tests/test_selenium/test_example_module.py
tests/test_selenium/test_examples.py
tests/test_selenium/test_node.py
tests/test_selenium/test_server.py
tests/test_selenium/test_tag.py
tests/test_selenium/tmpwoxt2qeq.py
tests/test_selenium/tmpzja14q4i.py
tests/test_selenium/testdir/test.css
wdom/__init__.py
wdom/css.py
wdom/document.py
wdom/element.py
wdom/event.py
wdom/node.py
wdom/options.py
wdom/parser.py
wdom/tag.py
wdom/util.py
wdom/web_node.py
wdom/window.py
wdom.egg-info/PKG-INFO
wdom.egg-info/SOURCES.txt
wdom.egg-info/dependency_links.txt
wdom.egg-info/not-zip-safe
wdom.egg-info/requires.txt
wdom.egg-info/top_level.txt
wdom/_static/css/bagpakk.min.css
wdom/_static/css/baseguide.min.css
wdom/_static/css/bijou.min.css
wdom/_static/css/groundwork.css
wdom/_static/css/kathamo.min.css
