Metadata-Version: 1.2
Name: wdom
Version: 0.3.1
Summary: GUI library for browser-based desktop applications
Home-page: https://github.com/miyakogi/wdom
Author: Hiroyuki Takagi
Author-email: miyako.dev@gmail.com
License: MIT
Keywords: dom browser gui ui
Platform: UNKNOWN
Classifier: Development Status :: 3 - Alpha
Classifier: Intended Audience :: Developers
Classifier: License :: OSI Approved :: MIT License
Classifier: Natural Language :: English
Classifier: Operating System :: OS Independent
Classifier: Programming Language :: Python :: 3
Classifier: Programming Language :: Python :: 3 :: Only
Classifier: Programming Language :: Python :: 3.5
Classifier: Programming Language :: Python :: 3.6
Classifier: Topic :: Software Development :: User Interfaces
Requires-Python: >=3.5.2
